python_scaffolder/__init__.py
python_scaffolder/py.typed
python_scaffolder-0.2.8.dist-info/METADATA
python_scaffolder-0.2.8.dist-info/WHEEL
python_scaffolder-0.2.8.dist-info/entry_points.txt
python_scaffolder-0.2.8.dist-info/RECORD
